mult_signo.v
//------------------------------------------------------------------------------
// Multiplicador con bypass para laRVa (Primera parte del proyecto)
// Mantiene la interfaz original para ser intercambiable con el núcleo existente.
//------------------------------------------------------------------------------

`timescale 1ns/1ps

module multiplier (
    input        clk,
    input        reset,
    input  [31:0]a,
    input  [31:0]b,
    input        ua,
    input        ub,
    input        hm,
    input        load,
    output       busy,
    output [31:0]out
);

    //--------------------------------------------------------------------------
    // Transformaciones de entrada: extensión de signo y módulo absoluto
    //--------------------------------------------------------------------------
    // Extensiones a 64 bits según el tratamiento con o sin signo. Se trabaja a
    // 64 bits porque el resultado del multiplicador ocupa ese ancho y así no
    // hay pérdida de información en el camino rápido.
    wire signed [63:0] a_ext = ua ? $signed({32'b0, a}) : $signed({{32{a[31]}}, a});
    wire signed [63:0] b_ext = ub ? $signed({32'b0, b}) : $signed({{32{b[31]}}, b});

    // Módulos absolutos para detectar potencias de dos (se usan valores
    // positivos porque en las potencias negativas solo cambia el signo final).
    wire [31:0] a_abs = (~ua & a[31]) ? (~a + 32'd1) : a;
    wire [31:0] b_abs = (~ub & b[31]) ? (~b + 32'd1) : b;

    //--------------------------------------------------------------------------
    // Detección de casos triviales
    //--------------------------------------------------------------------------
    // Cada una de estas banderas activa el camino rápido y evita la iteración
    // de 33 ciclos del multiplicador secuencial clásico.
    wire a_zero = (a == 32'd0);
    wire b_zero = (b == 32'd0);
    wire a_pos_one = (a == 32'd1);
    wire b_pos_one = (b == 32'd1);
    // en modo firmado, el valor 0xFFFF_FFFF equivale a -1, por eso se añade la
    // condición (~u?) que asegura que el operando se esté tratando con signo.
    wire a_neg_one = (~ua) & (a == 32'hFFFF_FFFF);
    wire b_neg_one = (~ub) & (b == 32'hFFFF_FFFF);

    // Potencias de dos (en valor absoluto). Se clona la lógica de detección
    // típica value & (value - 1) == 0 para evitar recurrir a módulos costosos.
    wire a_pow2 = (a_abs != 0) && ((a_abs & (a_abs - 1)) == 0);
    wire b_pow2 = (b_abs != 0) && ((b_abs & (b_abs - 1)) == 0);

    // Índice del bit a 1 usado para calcular el desplazamiento en potencias de dos
    // El bucle for recorre todos los bits y guarda la última posición en la que
    // encuentra un '1'. Para potencias de dos solo habrá un bit activo, por lo
    // que el resultado será el desplazamiento exacto.
    function automatic [5:0] bit_index32;
        input [31:0] value;
        integer idx;
        begin
            bit_index32 = 6'd0;
            for (idx = 0; idx < 32; idx = idx + 1)
                if (value[idx]) bit_index32 = idx[5:0];
        end
    endfunction

    wire [5:0] a_shift = bit_index32(a_abs);
    wire [5:0] b_shift = bit_index32(b_abs);

    wire a_neg = (~ua) & a[31];
    wire b_neg = (~ub) & b[31];

    //--------------------------------------------------------------------------
    // Camino rápido combinacional
    //--------------------------------------------------------------------------
    // Si 'fast_valid_c' es 1, el secuencial se inhibe y se devuelve el valor
    // calculado en 'fast_product_c'. Así se obtiene el resultado en un solo ciclo.
    reg        fast_valid_c;
    reg signed [63:0] fast_product_c;

    always @(*) begin
        fast_valid_c   = 1'b0;
        fast_product_c = 64'sd0;

        // Los casos se evalúan con prioridad. En cuanto se detecta uno válido
        // se calcula el producto correspondiente y se marca como disponible.
        if (a_zero || b_zero) begin
            fast_valid_c   = 1'b1;
            fast_product_c = 64'sd0;
        end else if (a_pos_one) begin
            fast_valid_c   = 1'b1;
            fast_product_c = b_ext;
        end else if (b_pos_one) begin
            fast_valid_c   = 1'b1;
            fast_product_c = a_ext;
        end else if (a_neg_one) begin
            fast_valid_c   = 1'b1;
            fast_product_c = -b_ext;
        end else if (b_neg_one) begin
            fast_valid_c   = 1'b1;
            fast_product_c = -a_ext;
        end else if (a_pow2) begin
            fast_valid_c   = 1'b1;
            fast_product_c = a_neg ? -(b_ext <<< a_shift) : (b_ext <<< a_shift);
        end else if (b_pow2) begin
            fast_valid_c   = 1'b1;
            fast_product_c = b_neg ? -(a_ext <<< b_shift) : (a_ext <<< b_shift);
        end
    end

    //--------------------------------------------------------------------------
    // Registros para conservar el resultado inmediato
    //--------------------------------------------------------------------------
    // 'fast_active' recuerda que la última operación se resolvió por bypass.
    // 'fast_product_r' guarda el resultado para que pueda leerse su parte alta
    // o baja cuando sea necesario (por ejemplo tras cambiar hm).
    reg        fast_active;
    reg signed [63:0] fast_product_r;

    always @(posedge clk or posedge reset) begin
        if (reset) begin
            fast_active    <= 1'b0;
            fast_product_r <= 64'sd0;
        end else if (load) begin
            fast_active    <= fast_valid_c;
            if (fast_valid_c) fast_product_r <= fast_product_c;
        end
    end

    // Cuando 'fast_valid_c' es 0 el kernel secuencial procesa la operación
    // exactamente igual que el multiplicador original de laRVa.
    // Núcleo secuencial original para los casos generales
    wire        seq_busy;
    wire [31:0] seq_out;

    multiplier_seq seq_core (
        .clk  (clk),
        .reset(reset),
        .a    (a),
        .b    (b),
        .ua   (ua),
        .ub   (ub),
        .hm   (hm),
        .load (load & ~fast_valid_c),  // si hay bypass, el núcleo secuencial no se activa
        .busy (seq_busy),
        .out  (seq_out)
    );

    // Salidas de la ruta rápida. Se reutilizan cuando 'hm' cambia; de esta forma
    // una misma operación sirve para MUL y MULH si se solicitan de manera
    // consecutiva.
    wire [31:0] fast_low  = fast_product_r[31:0];
    wire [31:0] fast_high = fast_product_r[63:32];

    // Multiplexores finales. Cuando el camino rápido tuvo éxito se ignora el
    // 'busy' secuencial y se entrega directamente el resultado almacenado.
    assign busy = fast_active ? 1'b0 : seq_busy;
    assign out  = fast_active ? (hm ? fast_high : fast_low) : seq_out;

endmodule

//------------------------------------------------------------------------------
// Núcleo secuencial original renombrado (idéntico al de laRVa.v)
// Este bloque se mantiene sin cambios funcionales para garantizar que el
// procesador sigue viendo la misma temporización cuando no aplica el bypass.
//------------------------------------------------------------------------------
module multiplier_seq (
    input        clk,
    input        reset,
    input  [31:0]a,
    input  [31:0]b,
    input        ua,
    input        ub,
    input        hm,
    input        load,
    output       busy,
    output [31:0]out
);

    // Banco de registros interno que almacena los operandos y su modo de signo.
    // Esto permite detectar cuándo se repite la misma multiplicación y reutilizar
    // el resultado sin reactivar la máquina de estados.
    reg [31:0] oa;
    reg [31:0] ob;
    reg        oua;
    reg        oub;
    always @(posedge clk or posedge reset) begin
        if (reset) {oua, oa} <= 0;
        else if (load) {oua, oa} <= {ua, a};
    end
    always @(posedge clk or posedge reset) begin
        if (reset) {oub, ob} <= 0;
        else if (load) {oub, ob} <= {ub, b};
    end

    wire iload = load & (({oa, ob} != {a, b}) | (hm & ({oua, oub} != {ua, ub})));

    // Ajuste de signo de entrada. 'sma' indica si el multiplicador es negativo
    // en modo firmado. Si lo es, se invierten ambos operandos para que la parte
    // secuencial trabaje solo con magnitudes positivas.
    wire        sma = (~ua) & a[31];
    wire [31:0] ma  = (sma ? (~a) : a) + sma;
    wire [31:0] mb  = (sma ? (~b) : b) + sma;

    // Registro desplazador del multiplicador. Cada ciclo desplaza un bit hacia
    // la derecha y sirve de contador de los 32 pasos necesarios.
    reg [31:0] sha = 0;
    always @(posedge clk or posedge reset) begin
        if (reset) sha <= 0;
        else sha <= iload ? ma : {1'b0, sha[31:1]};
    end
    // 'busy' permanece activo mientras exista algún bit pendiente en el
    // desplazador o mientras se está cargando una nueva operación.
    assign busy = iload | (|sha);

    // Registro desplazador del multiplicando extendido a 64 bits. Su LSB se
    // suma al acumulador cuando el bit actual del multiplicador es 1.
    reg [63:0] shb;
    always @(posedge clk)
        shb <= iload ? (ub ? {32'b0, mb} : {{32{mb[31]}}, mb}) : {shb[62:0], 1'b0};

    // Acumulador: almacena la suma parcial de los productos desplazados, igual
    // que en el diseño original. Cuando 'iload' es 1 se reinicia a cero.
    reg [63:0] acc;
    always @(posedge clk or posedge reset) begin
        if (reset) acc <= 0;
        else if (iload | sha[0]) acc <= iload ? 64'd0 : acc + shb;
    end

    // Selección de palabra alta/baja del acumulador, sin cambios respecto a laRVa.
    assign out = hm ? acc[63:32] : acc[31:0];
endmodule

multiplier_4bit_tb.v
`timescale 1ns/1ps
//`include "mult_signo.v"
module multiplier_4bit_tb;

    // Señales del DUT (Device Under Test)
    reg clk;
    reg reset;
    reg [31:0] a;
    reg [31:0] b;
    reg ua;
    reg ub;
    reg hm;
    reg load;
    wire busy;
    wire [31:0] out;
    
    // Variables auxiliares para verificación
    reg [63:0] resultado_esperado;
    reg [63:0] resultado_capturado;
    integer errores;
    integer pruebas;
    
    // Instanciar el DUT
//   multiplier_4bit_sequential DUT (
	multiplier DUT(		// Jesus Arias implementation
        .clk(clk),
        .reset(reset),
        .a(a),
        .b(b),
        .ua(ua),
        .ub(ub),
        .hm(hm),
        .load(load),
        .busy(busy),
        .out(out)
    );
    
    // Generador de reloj
    initial begin
        clk = 0;
        forever #5 clk = ~clk;  // Periodo de 10ns
    end
    
    // Tareas auxiliares
    
    // Tarea para calcular resultado esperado
    task calcular_esperado;
        input [31:0] op_a;
        input [31:0] op_b;
        input unsigned_a;
        input unsigned_b;
        output [63:0] esperado;
        begin
            if (unsigned_a && unsigned_b) begin
                // Ambos sin signo
                esperado = op_a * op_b;
            end else if (!unsigned_a && !unsigned_b) begin
                // Ambos con signo
                esperado = {{32{op_a[31]}},op_a} * {{32{op_b[31]}},op_b};
 //               esperado = $signed(op_a) * $signed(op_b);
            end else if (!unsigned_a && unsigned_b) begin
                // a con signo, b sin signo
                esperado = {{32{op_a[31]}},op_a} * op_b;
            end else begin
                // a sin signo, b con signo
                esperado = op_a * {{32{op_b[31]}},op_b};
            end
        end
    endtask
    
    // Tarea para ejecutar una multiplicación
    task ejecutar_multiplicacion;
        input [31:0] op_a;
        input [31:0] op_b;
        input unsigned_a;
        input unsigned_b;
        input obtener_high;
        input [255:0] descripcion;
        begin
            $display("\n=== Prueba %0d: %0s ===", pruebas + 1, descripcion);
            $display("A = %d (0x%08h), B = %d (0x%08h)", 
                     unsigned_a ? op_a : $signed(op_a), op_a,
                     unsigned_b ? op_b : $signed(op_b), op_b);
            $display("UA = %b, UB = %b, HM = %b", unsigned_a, unsigned_b, obtener_high);
            
            // Configurar operación
            a = op_a;
            b = op_b;
            ua = unsigned_a;
            ub = unsigned_b;
            hm = obtener_high;
            
            // Calcular resultado esperado
            calcular_esperado(op_a, op_b, unsigned_a, unsigned_b, resultado_esperado);
            
            // Iniciar multiplicación
            #2 load = 1;
            #10 load = 0;

            // Esperar a que termine
            wait (!busy);
			#2;	// aparece el resultado más tarde

            // ---- AÑadido por Mario Medrano: Ver resultados en decimal con signo ------------------------
            // Capturar resultado de palabra baja
            if (!obtener_high) begin
                resultado_capturado = out;
                $display("Resultado (low): 0x%08h (%d)", out, $signed(out));
                $display("Esperado  (low): 0x%08h (%d)", resultado_esperado[31:0], $signed(resultado_esperado[31:0]));
           
                
                if (out !== resultado_esperado[31:0]) begin
                    $display("ERROR: Resultado incorrecto en palabra baja!");
                    errores = errores + 1;
                end else begin
                    $display("CORRECTO: Palabra baja");
                end
            end
            
            // Para verificar palabra alta, ejecutar de nuevo con hm=1
            if (obtener_high) begin
                // Siempre verificar palabra alta

//               while (busy);
                resultado_capturado = out;             
                $display("Resultado (high): 0x%08h (%d)", out, $signed(out));
                $display("Esperado  (high): 0x%08h (%d)", resultado_esperado[63:32], $signed(resultado_esperado[63:32]));
                
                if (out !== resultado_esperado[63:32]) begin
                    $display("ERROR: Resultado incorrecto en palabra alta!");
                    errores = errores + 1;
                end else begin
                    $display("CORRECTO: Palabra alta");
                end
            end
            
            pruebas = pruebas + 1;
            @(posedge clk);
        end
    endtask
    
    // Programa principal de pruebas
    initial begin
        // Inicialización
        $dumpfile("multiplier_4bit_tb.vcd");
        $dumpvars(0, multiplier_4bit_tb);
        
        errores = 0;
        pruebas = 0;
        reset = 1;
        a = 0;
        b = 0;
        ua = 0;
        ub = 0;
        hm = 0;
        load = 0;
        
        // Reset del sistema
        #20 reset = 0;
        @(posedge clk);
        
        $display("\n========================================");
        $display("  INICIO DE PRUEBAS DEL MULTIPLICADOR");
        $display("========================================");
        // PRUEBA 1: Números pequeños positivos (parte baja)
        ejecutar_multiplicacion(32'd5, 32'd7, 1, 1, 0, "Num bajos ++ (5 x 7) low");
        // PRUEBA 2: Números pequeños positivos (parte alta)
        ejecutar_multiplicacion(32'd5, 32'd7, 1, 1, 1, "Num bajos ++ (5 x 7) high");
        // PRUEBA 3: Números pequeños con diferente signo (parte baja)
        ejecutar_multiplicacion(32'd5, -32'd7, 1, 0, 0, "Num bajos +- (5 x -7) low");
        // PRUEBA 4: Números pequeños con diferente signo (parte alta)
        ejecutar_multiplicacion(32'd5, -32'd7, 1, 0, 1, "Num bajos +- (5 x -7) high");
        // PRUEBA 5: Números pequeños con diferente signo (parte baja)
        ejecutar_multiplicacion(-32'd5, 32'd7, 0, 0, 0, "Num bajos -+ (-5 x 7) low");
        // PRUEBA 6: Números pequeños con diferente signo (parte alta)
        ejecutar_multiplicacion(-32'd5, 32'd7, 0, 0, 1, "Num bajos -+ (-5 x 7) high");
        // PRUEBA 7: Números pequeños ambos negativos
        ejecutar_multiplicacion(-32'd5, -32'd7, 0, 0, 0, "Num bajos -- (-5 x -7) low");
        // PRUEBA 8: Números pequeños ambos negativos
        ejecutar_multiplicacion(-32'd5, -32'd7, 0, 0, 1, "Num bajos -- (-5 x -7) high");
        
        // PRUEBA 9: Multiplicación por cero
        ejecutar_multiplicacion(32'd12345, 32'd0, 1, 1, 0, "Multando = 0 low");
        // PRUEBA 10: Multiplicación por cero
        ejecutar_multiplicacion(32'd12345, 32'd0, 1, 1, 1, "Multando = 0 high");
        // PRUEBA 11: Multiplicación por cero
        ejecutar_multiplicacion(32'd0, 32'd12345, 1, 1, 0, "Mulor = 0 low");
        // PRUEBA 12: Multiplicación por cero
        ejecutar_multiplicacion(32'd0, 32'd12345, 1, 1, 1, "Mulor = 0 high");
        
        // PRUEBA 13: Multiplicación por uno
        ejecutar_multiplicacion(32'd12345, 32'd1, 1, 1, 0, "Multiplicacion por 1 low");
        // PRUEBA 14: Multiplicación por uno
        ejecutar_multiplicacion(32'd12345, 32'd1, 1, 1, 1, "Multiplicacion por 1 high");
        // PRUEBA 15: Multiplicación por -1
        ejecutar_multiplicacion(32'd12345, -32'd1, 1, 0, 0, "Multiplicacion por -1 low");
        // PRUEBA 16: Multiplicación por -1
        ejecutar_multiplicacion(32'd12345, -32'd1, 1, 0, 1, "Multiplicacion por -1 high");
        
        // PRUEBA 17: Números muy grandes sin signo
        ejecutar_multiplicacion(32'hFFFFFFFF, 32'hFFFFFFFF, 1, 1, 0, 
                              "altos unsigned (2^32-1 x 2^32-1) low");
        // PRUEBA 18: Números muy grandes sin signo
        ejecutar_multiplicacion(32'hFFFFFFFF, 32'hFFFFFFFF, 1, 1, 1, 
                              "altos unsigned (2^32-1 x 2^32-1) high");
        
        // PRUEBA 19: Números grandes con signo positivo
        ejecutar_multiplicacion(32'h7FFFFFFF, 32'h7FFFFFFF, 0, 0, 0, 
                              "altos signed + (2^31-1 x 2^31-1) low");
        // PRUEBA 20: Números grandes con signo positivo
        ejecutar_multiplicacion(32'h7FFFFFFF, 32'h7FFFFFFF, 0, 0, 1, 
                              "altos signed + (2^31-1 x 2^31-1) high");
        
        // PRUEBA 21: Números grandes con diferente signo
        ejecutar_multiplicacion(32'h7FFFFFFF, 32'h80000000, 0, 0, 0, 
                              "grande signo + x grande signo low");
        // PRUEBA 22: Números grandes con diferente signo
        ejecutar_multiplicacion(32'h7FFFFFFF, 32'h80000000, 0, 0, 1, 
                              "grande signo + x grande signo high");
        
        // PRUEBA 23: Casos de overflow intermedio
       ejecutar_multiplicacion(32'h10000, 32'h10000, 1, 1, 0, 
                              "65536 x 65536 (overflow a palabra alta) low");
        // PRUEBA 24: Casos de overflow intermedio
       ejecutar_multiplicacion(32'h10000, 32'h10000, 1, 1, 1, 
                              "65536 x 65536 (overflow a palabra alta) high");
        
        // PRUEBA 25: Patrones de bits especiales
        ejecutar_multiplicacion(32'h55555555, 32'hAAAAAAAA, 1, 1, 0, 
                              "signed (0x5555... x 0xAAAA...) low");
        // PRUEBA 26: Patrones de bits especiales
        ejecutar_multiplicacion(32'h55555555, 32'hAAAAAAAA, 1, 1, 1, 
                              "signed (0x5555... x 0xAAAA...) high");
        
        // PRUEBA 27: Números con muchos ceros en nibbles
        ejecutar_multiplicacion(32'h00FF00FF, 32'h0F0F0F0F, 1, 1, 0, 
                              "Numeros con nibbles cero low");
        // PRUEBA 28: Números con muchos ceros en nibbles
        ejecutar_multiplicacion(32'h00FF00FF, 32'h0F0F0F0F, 1, 1, 1, 
                              "Numeros con nibbles cero high");
        
        // PRUEBA 29: Potencias de 2
        ejecutar_multiplicacion(32'd1024, 32'd2048, 1, 1, 0, 
                              "Potencias de 2 (1024 x 2048)low");
        // PRUEBA 30: Potencias de 2
        ejecutar_multiplicacion(32'd1024, 32'd2048, 1, 1, 1, 
                              "Potencias de 2 (1024 x 2048)high");
        
        // PRUEBA 31: Números primos grandes
        ejecutar_multiplicacion(32'd65537, 32'd65521, 1, 1, 0, 
                              "Numeros primos grandes low");
        // PRUEBA 32: Números primos grandes
        ejecutar_multiplicacion(32'd65537, 32'd65521, 1, 1, 1, 
                              "Numeros primos grandes high");

        // PRUEBA 33: Maximo sin signo x -1       
        ejecutar_multiplicacion(32'hFFFFFFFF, -32'd1, 1, 0, 0, 
                              "Maximo sin signo x -1 low");
        // PRUEBA 34: Maximo sin signo x -1       
        ejecutar_multiplicacion(32'hFFFFFFFF, -32'd1, 1, 0, 1, 
                              "Maximo sin signo x -1 high");
        
        // PRUEBA 35: Números aleatorios
        ejecutar_multiplicacion(32'd123456789, 32'd987654321, 1, 1, 0, 
                              "Numeros aleatorios grandes low");
        // PRUEBA 36: Números aleatorios
        ejecutar_multiplicacion(32'd123456789, 32'd987654321, 1, 1, 1, 
                              "Numeros aleatorios grandes high");
        
        // PRUEBA 37: Caso especial -1 x -1
        ejecutar_multiplicacion(32'hFFFFFFFF, 32'hFFFFFFFF, 0, 0, 0, 
                              "(-1) x (-1) con signo, low");
        // PRUEBA 38: Caso especial -1 x -1
        ejecutar_multiplicacion(32'hFFFFFFFF, 32'hFFFFFFFF, 0, 0, 1, 
                              "(-1) x (-1) con signo, high");

        // PRUEBA 39: Número maximo con signo negativo en A
        ejecutar_multiplicacion(32'h80000000, 32'hFFFFFFFF, 0, 0, 0, 
                              "max signed - (-2^31-1 x -1) low");
        // PRUEBA 40: Número maximo con signo negativo en A
        ejecutar_multiplicacion(32'h80000000, 32'hFFFFFFFF, 0, 0, 1, 
                              "max signed - (-2^31-1 x -1) high");
        
        // PRUEBA 41: Número maximo con signo negativo en B
        ejecutar_multiplicacion(32'hFFFFFFFF, 32'h80000000, 0, 0, 0, 
                              "max signed - (-1 x -2^31-1) low");
        // PRUEBA 42: Número maximo con signo negativo en B
        ejecutar_multiplicacion(32'hFFFFFFFF, 32'h80000000, 0, 0, 1, 
                              "max signed - (-1 x -2^31-1) high");
        
        // PRUEBA 43: Números max con signo negativo
        ejecutar_multiplicacion(32'h80000000, 32'h80000000, 0, 0, 0, 
                              "max signo - (-2^31 x -2^31) low");
        // PRUEBA 44: Números max con signo negativo
        ejecutar_multiplicacion(32'h80000000, 32'h80000000, 0, 0, 1, 
                              "max signo - (-2^31 x -2^31) high");
        

        
        // Resumen final
        $display("\n========================================");
        $display("  RESUMEN DE PRUEBAS");
        $display("========================================");
        $display("Total de pruebas ejecutadas: %0d", pruebas);
        $display("Errores encontrados: %0d", errores);
        if (errores == 0) begin
            $display("¡TODAS LAS PRUEBAS PASARON EXITOSAMENTE!");
        end else begin
            $display("ATENCION: Se encontraron errores en las pruebas");
        end
        $display("========================================\n");
        
        // Esperar un poco antes de terminar
        #100;
        $finish;
    end
    
    // Monitor para debugging
    // initial begin
    //     $monitor("Tiempo=%0t, Estado: reset=%b, load=%b, busy=%b, ciclo_actual=%d", 
    //              $time, reset, load, busy, DUT.clk);
    // end


endmodule

multiplier_4bit_tb.vcd
$date
	Wed Nov 19 18:46:20 2025
$end
$version
	Icarus Verilog
$end
$timescale
	1ps
$end
$scope module multiplier_4bit_tb $end
$var wire 1 ! busy $end
$var wire 32 " out [31:0] $end
$var reg 32 # a [31:0] $end
$var reg 32 $ b [31:0] $end
$var reg 1 % clk $end
$var integer 32 & errores [31:0] $end
$var reg 1 ' hm $end
$var reg 1 ( load $end
$var integer 32 ) pruebas [31:0] $end
$var reg 1 * reset $end
$var reg 64 + resultado_capturado [63:0] $end
$var reg 64 , resultado_esperado [63:0] $end
$var reg 1 - ua $end
$var reg 1 . ub $end
$scope module DUT $end
$var wire 32 / a [31:0] $end
$var wire 32 0 a_abs [31:0] $end
$var wire 64 1 a_ext [63:0] $end
$var wire 1 2 a_neg $end
$var wire 1 3 a_neg_one $end
$var wire 1 4 a_pos_one $end
$var wire 1 5 a_pow2 $end
$var wire 6 6 a_shift [5:0] $end
$var wire 1 7 a_zero $end
$var wire 32 8 b [31:0] $end
$var wire 32 9 b_abs [31:0] $end
$var wire 64 : b_ext [63:0] $end
$var wire 1 ; b_neg $end
$var wire 1 < b_neg_one $end
$var wire 1 = b_pos_one $end
$var wire 1 > b_pow2 $end
$var wire 6 ? b_shift [5:0] $end
$var wire 1 @ b_zero $end
$var wire 1 ! busy $end
$var wire 1 A clk $end
$var wire 32 B fast_high [31:0] $end
$var wire 32 C fast_low [31:0] $end
$var wire 1 D hm $end
$var wire 1 E load $end
$var wire 32 F out [31:0] $end
$var wire 1 G reset $end
$var wire 1 H seq_busy $end
$var wire 32 I seq_out [31:0] $end
$var wire 1 J ua $end
$var wire 1 K ub $end
$var reg 1 L fast_active $end
$var reg 64 M fast_product_c [63:0] $end
$var reg 64 N fast_product_r [63:0] $end
$var reg 1 O fast_valid_c $end
$scope function bit_index32 $end
$upscope $end
$scope module seq_core $end
$var wire 32 P a [31:0] $end
$var wire 32 Q b [31:0] $end
$var wire 1 H busy $end
$var wire 1 A clk $end
$var wire 1 D hm $end
$var wire 1 R iload $end
$var wire 1 S load $end
$var wire 32 T ma [31:0] $end
$var wire 32 U mb [31:0] $end
$var wire 32 V out [31:0] $end
$var wire 1 G reset $end
$var wire 1 W sma $end
$var wire 1 J ua $end
$var wire 1 K ub $end
$var reg 64 X acc [63:0] $end
$var reg 32 Y oa [31:0] $end
$var reg 32 Z ob [31:0] $end
$var reg 1 [ oua $end
$var reg 1 \ oub $end
$var reg 32 ] sha [31:0] $end
$var reg 64 ^ shb [63:0] $end
$upscope $end
$upscope $end
$scope task calcular_esperado $end
$var reg 64 _ esperado [63:0] $end
$var reg 32 ` op_a [31:0] $end
$var reg 32 a op_b [31:0] $end
$var reg 1 b unsigned_a $end
$var reg 1 c unsigned_b $end
$upscope $end
$scope task ejecutar_multiplicacion $end
$var reg 256 d descripcion [255:0] $end
$var reg 1 e obtener_high $end
$var reg 32 f op_a [31:0] $end
$var reg 32 g op_b [31:0] $end
$var reg 1 h unsigned_a $end
$var reg 1 i unsigned_b $end
$upscope $end
$upscope $end
$enddefinitions $end
#0
$dumpvars
xi
xh
bx g
bx f
xe
bx d
xc
xb
bx a
bx `
bx _
bx ^
b0 ]
0\
0[
b0 Z
b0 Y
b0 X
0W
b0 V
b0 U
b0 T
0S
0R
b0 Q
b0 P
1O
b0 N
b0 M
0L
0K
0J
b0 I
0H
1G
b0 F
0E
0D
b0 C
b0 B
0A
1@
b0 ?
0>
0=
0<
0;
b0 :
b0 9
b0 8
17
b0 6
05
04
03
02
b0 1
b0 0
b0 /
0.
0-
bx ,
bx +
1*
b0 )
0(
0'
b0 &
0%
b0 $
b0 #
b0 "
0!
$end
#5000
bx0 ^
1%
1A
#10000
0%
0A
#15000
bx00 ^
1%
1A
#20000
0%
0A
0*
0G
#25000
bx000 ^
b10 ?
b10 6
b111 :
b111 9
b111 U
b101 1
b101 0
0O
b101 T
b100011 ,
b100011 _
1c
1b
b111 a
b101 `
1.
1K
1-
1J
b111 $
b111 8
b111 Q
0@
b101 #
b101 /
b101 P
07
b10011100111010101101101001000000110001001100001011010100110111101110011001000000010101100101011001000000010100000110101001000000111100000100000001101110010100100100000011011000110111101110111 d
0e
1i
1h
b111 g
b101 f
1%
1A
#27000
1!
1H
1R
1S
1(
1E
#30000
0%
0A
#35000
0R
1[
b101 Y
1\
b111 Z
b101 ]
b111 ^
1%
1A
#37000
0S
0(
0E
#40000
0%
0A
#45000
b111 "
b111 F
b111 I
b111 V
b111 X
b10 ]
b1110 ^
1%
1A
#50000
0%
0A
#55000
b1 ]
b11100 ^
1%
1A
#60000
0%
0A
#65000
b100011 "
b100011 F
b100011 I
b100011 V
0!
0H
b100011 X
b0 ]
b111000 ^
1%
1A
#67000
b1 )
b100011 +
#70000
0%
0A
#75000
b1110000 ^
b0 "
b0 F
b0 I
b0 V
1'
1D
b1001110011101010110110100100000011000100110000101101010011011110111001100100000001010110010101100100000001010000011010100100000011110000010000000110111001010010010000001101000011010010110011101101000 d
1e
1%
1A
#77000
1S
1(
1E
#80000
0%
0A
#85000
b11100000 ^
1%
1A
#87000
0S
0(
0E
#89000
b10 )
b0 +
#90000
0%
0A
#95000
b111000000 ^
b100011 "
b100011 F
b10 ?
1;
b100011 I
b100011 V
b1111111111111111111111111111111111111111111111111111111111111001 :
b111 9
b11111111111111111111111111111001 U
b1111111111111111111111111111111111111111111111111111111111011101 ,
b1111111111111111111111111111111111111111111111111111111111011101 _
0c
b11111111111111111111111111111001 a
0'
0D
0.
0K
b11111111111111111111111111111001 $
b11111111111111111111111111111001 8
b11111111111111111111111111111001 Q
b1001110011101010110110100100000011000100110000101101010011011110111001100100000001010110010110100100000001010000011010100100000011110000010000000101101001101110010100100100000011011000110111101110111 d
0e
0i
b11111111111111111111111111111001 g
1%
1A
#97000
1!
1H
1R
1S
1(
1E
#100000
0%
0A
#105000
b0 "
b0 F
b0 I
b0 V
0R
b0 X
b101 ]
0\
b11111111111111111111111111111001 Z
b1111111111111111111111111111111111111111111111111111111111111001 ^
1%
1A
#107000
0S
0(
0E
#110000
0%
0A
#115000
b11111111111111111111111111111001 "
b11111111111111111111111111111001 F
b11111111111111111111111111111001 I
b11111111111111111111111111111001 V
b10 ]
b1111111111111111111111111111111111111111111111111111111111111001 X
b1111111111111111111111111111111111111111111111111111111111110010 ^
1%
1A
#120000
0%
0A
#125000
b1 ]
b1111111111111111111111111111111111111111111111111111111111100100 ^
1%
1A
#130000
0%
0A
#135000
b11111111111111111111111111011101 "
b11111111111111111111111111011101 F
0!
b11111111111111111111111111011101 I
b11111111111111111111111111011101 V
0H
b0 ]
b1111111111111111111111111111111111111111111111111111111111011101 X
b1111111111111111111111111111111111111111111111111111111111001000 ^
1%
1A
#137000
b11 )
b11111111111111111111111111011101 +
#140000
0%
0A
#145000
b1111111111111111111111111111111111111111111111111111111110010000 ^
b11111111111111111111111111111111 "
b11111111111111111111111111111111 F
b11111111111111111111111111111111 I
b11111111111111111111111111111111 V
1'
1D
b100111001110101011011010010000001100010011000010110101001101111011100110010000000101011001011010010000000101000001101010010000001111000001000000010110100110111001010010010000001101000011010010110011101101000 d
1e
1%
1A
#147000
1S
1(
1E
#150000
0%
0A
#155000
b1111111111111111111111111111111111111111111111111111111100100000 ^
1%
1A
#157000
0S
0(
0E
#159000
b100 )
b11111111111111111111111111111111 +
#160000
0%
0A
#165000
b1111111111111111111111111111111111111111111111111111111001000000 ^
b11111111111111111111111111011101 "
b11111111111111111111111111011101 F
0;
b10 6
12
1W
b11111111111111111111111111011101 I
b11111111111111111111111111011101 V
b111 :
b11111111111111111111111111111001 U
b1111111111111111111111111111111111111111111111111111111111111011 1
b101 0
b101 T
0b
b111 a
b11111111111111111111111111111011 `
0'
0D
0-
0J
b111 $
b111 8
b111 Q
b11111111111111111111111111111011 #
b11111111111111111111111111111011 /
b11111111111111111111111111111011 P
b1001110011101010110110100100000011000100110000101101010011011110111001100100000001011010010101100100000001010000010110100110101001000000111100000100000001101110010100100100000011011000110111101110111 d
0e
0h
b111 g
b11111111111111111111111111111011 f
1%
1A
#167000
1!
1H
1R
1S
1(
1E
#170000
0%
0A
#175000
b0 "
b0 F
0R
b0 I
b0 V
0[
b11111111111111111111111111111011 Y
b111 Z
b101 ]
b0 X
b1111111111111111111111111111111111111111111111111111111111111001 ^
1%
1A
#177000
0S
0(
0E
#180000
0%
0A
#185000
b11111111111111111111111111111001 "
b11111111111111111111111111111001 F
b11111111111111111111111111111001 I
b11111111111111111111111111111001 V
b1111111111111111111111111111111111111111111111111111111111111001 X
b10 ]
b1111111111111111111111111111111111111111111111111111111111110010 ^
1%
1A
#190000
0%
0A
#195000
b1 ]
b1111111111111111111111111111111111111111111111111111111111100100 ^
1%
1A
#200000
0%
0A
#205000
b11111111111111111111111111011101 "
b11111111111111111111111111011101 F
b11111111111111111111111111011101 I
b11111111111111111111111111011101 V
0!
0H
b1111111111111111111111111111111111111111111111111111111111011101 X
b0 ]
b1111111111111111111111111111111111111111111111111111111111001000 ^
1%
1A
#207000
b101 )
b11111111111111111111111111011101 +
#210000
0%
0A
#215000
b1111111111111111111111111111111111111111111111111111111110010000 ^
b11111111111111111111111111111111 "
b11111111111111111111111111111111 F
b11111111111111111111111111111111 I
b11111111111111111111111111111111 V
1'
1D
b100111001110101011011010010000001100010011000010110101001101111011100110010000000101101001010110010000000101000001011010011010100100000011110000010000000110111001010010010000001101000011010010110011101101000 d
1e
1%
1A
#217000
1S
1(
1E
#220000
0%
0A
#225000
b1111111111111111111111111111111111111111111111111111111100100000 ^
1%
1A
#227000
0S
0(
0E
#229000
b110 )
b11111111111111111111111111111111 +
#230000
0%
0A
